pylua_vm/__init__.py
pylua_vm/exceptions.py
pylua_vm/interactive_session.py
pylua_vm/lua_process.py
pylua_vm/networking.py
pylua_vm/vm_manager.py
pylua_bioxen_vm-0.1.3.dist-info/LICENSE
pylua_bioxen_vm-0.1.3.dist-info/METADATA
pylua_bioxen_vm-0.1.3.dist-info/WHEEL
pylua_bioxen_vm-0.1.3.dist-info/top_level.txt
pylua_bioxen_vm-0.1.3.dist-info/RECORD
