Metadata-Version: 2.1
Name: pylua-bioxen-vm
Version: 0.1.3
Summary: Process-isolated networked Lua VMs managed from Python (extracted from BioXen)
Home-page: UNKNOWN
License: UNKNOWN
Platform: UNKNOWN
Requires-Python: >=3.7
License-File: LICENSE
